debarcer/__init__.py
debarcer/command_line.py
debarcer/debarcer.py
debarcer/find_regions_coverage.py
debarcer/generate_consensus.py
debarcer/generate_plots.py
debarcer/generate_report.py
debarcer/generate_vcf.py
debarcer/preprocess_fastqs.py
debarcer/run_analyses.py
debarcer/umi_error_correct.py
debarcer/umi_network_collapse.py
debarcer/utilities.py
debarcer/version.py
debarcer/src/__init__.py
debarcer/src/find_regions_coverage.py
debarcer/src/generate_consensus.py
debarcer/src/generate_plots.py
debarcer/src/generate_report.py
debarcer/src/generate_vcf.py
debarcer/src/preprocess_fastqs.py
debarcer/src/run_analyses.py
debarcer/src/umi_error_correct.py
debarcer/src/umi_network_collapse.py
debarcer/src/utilities.py
debarcer/src/version.py
debarcer-2.1.4.dist-info/LICENSE
debarcer-2.1.4.dist-info/METADATA
debarcer-2.1.4.dist-info/WHEEL
debarcer-2.1.4.dist-info/entry_points.txt
debarcer-2.1.4.dist-info/top_level.txt
debarcer-2.1.4.dist-info/RECORD
