Metadata-Version: 2.1
Name: debarcer
Version: 2.1.4
Summary: A package for de-barcoding and error correction of sequencing data containing molecular barcodes.
Home-page: https://github.com/oicr-gsi/debarcer
Author: Richard Jovelin
Author-email: richard.jovelin@oicr.on.ca
License: MIT License
Keywords: computational genomics
Platform: UNKNOWN
Classifier: Development Status :: 3 - Alpha
Classifier: Intended Audience :: Science/Research
Classifier: Intended Audience :: Developers
Classifier: License :: OSI Approved :: MIT License
Classifier: Programming Language :: Python :: 3
Classifier: Programming Language :: Python :: 3.6
Classifier: Topic :: Software Development
Classifier: Topic :: Scientific/Engineering
Classifier: Operating System :: POSIX
Classifier: Operating System :: Unix
Classifier: Operating System :: MacOS
Requires-Python: >=3.6
Requires-Dist: numpy (>=1.14.2)
Requires-Dist: pandas (>=0.22.0)
Requires-Dist: pysam (>=0.14.1)
Requires-Dist: matplotlib (>=3.1.2)
Requires-Dist: mistune (>=0.8.4)
Requires-Dist: networkx (>=1.11)
Requires-Dist: pygal (>=2.4.0)
Requires-Dist: scipy (>=1.0.1)
Requires-Dist: seaborn (>=0.9.0)
Requires-Dist: pyyaml (>=5.1.1)
